{
  "frame_id": "000",
  "targets": [
    {
      "id": 0,
      "x": 118.153,
      "y": 2.789,
      "range": 118.186,
      "azimuth": 0.0236,
      "velocity": 18.39,
      "rcs": 19.92
    },
    {
      "id": 1,
      "x": 69.126,
      "y": 5.93,
      "range": 69.379,
      "azimuth": 0.0856,
      "velocity": 8.78,
      "rcs": 13.34
    },
    {
      "id": 2,
      "x": 26.399,
      "y": -3.811,
      "range": 26.673,
      "azimuth": -0.1434,
      "velocity": -3.31,
      "rcs": 23.05
    },
    {
      "id": 3,
      "x": 138.135,
      "y": 5.844,
      "range": 138.258,
      "azimuth": 0.0423,
      "velocity": 24.77,
      "rcs": 20.44
    },
    {
      "id": 4,
      "x": 92.386,
      "y": 7.091,
      "range": 92.657,
      "azimuth": 0.0766,
      "velocity": -4.31,
      "rcs": 18.12
    },
    {
      "id": 5,
      "x": 62.724,
      "y": 7.188,
      "range": 63.135,
      "azimuth": 0.1141,
      "velocity": 24.21,
      "rcs": 10.82
    },
    {
      "id": 6,
      "x": 19.105,
      "y": -2.942,
      "range": 19.33,
      "azimuth": -0.1528,
      "velocity": 6.47,
      "rcs": 29.58
    },
    {
      "id": 7,
      "x": 71.599,
      "y": -9.351,
      "range": 72.207,
      "azimuth": -0.1299,
      "velocity": 15.41,
      "rcs": 16.26
    },
    {
      "id": 8,
      "x": 8.088,
      "y": -9.091,
      "range": 12.168,
      "azimuth": -0.8437,
      "velocity": 11.9,
      "rcs": 14.64
    },
    {
      "id": 9,
      "x": 8.893,
      "y": 5.118,
      "range": 10.26,
      "azimuth": 0.5222,
      "velocity": 2.23,
      "rcs": 22.08
    },
    {
      "id": 10,
      "x": 91.658,
      "y": -9.417,
      "range": 92.141,
      "azimuth": -0.1024,
      "velocity": 0.2,
      "rcs": 14.78
    }
  ],
  "radar_params": {
    "yaw": 0.03,
    "x_offset": 3.5,
    "y_offset": 0.0
  }
}